graphtheory/__init__.py
graphtheory/algorithms/__init__.py
graphtheory/algorithms/acyclic.py
graphtheory/algorithms/closure.py
graphtheory/algorithms/matching.py
graphtheory/algorithms/topsort.py
graphtheory/algorithms/tests/__init__.py
graphtheory/algorithms/tests/test_acyclic.py
graphtheory/algorithms/tests/test_closure.py
graphtheory/algorithms/tests/test_matching.py
graphtheory/algorithms/tests/test_topsort.py
graphtheory/approximation/__init__.py
graphtheory/approximation/tests/__init__.py
graphtheory/bipartiteness/__init__.py
graphtheory/bipartiteness/bipartite.py
graphtheory/bipartiteness/hopcroftkarp.py
graphtheory/bipartiteness/matching.py
graphtheory/bipartiteness/tests/__init__.py
graphtheory/bipartiteness/tests/clique1.py
graphtheory/bipartiteness/tests/test_bipartite.py
graphtheory/bipartiteness/tests/test_hopcroftkarp.py
graphtheory/bipartiteness/tests/test_matching.py
graphtheory/chordality/__init__.py
graphtheory/chordality/chordalcover.py
graphtheory/chordality/chordaldset.py
graphtheory/chordality/chordaltools.py
graphtheory/chordality/intervalbfs.py
graphtheory/chordality/intervaldfs.py
graphtheory/chordality/intervaltools.py
graphtheory/chordality/mcsm.py
graphtheory/chordality/mdotools.py
graphtheory/chordality/peotools.py
graphtheory/chordality/tdtools.py
graphtheory/chordality/tests/__init__.py
graphtheory/chordality/tests/grotzsch.py
graphtheory/chordality/tests/pathwidth1.py
graphtheory/chordality/tests/pathwidth2.py
graphtheory/chordality/tests/test_chordalcover.py
graphtheory/chordality/tests/test_chordaldset.py
graphtheory/chordality/tests/test_chordaltools.py
graphtheory/chordality/tests/test_intervalbfs.py
graphtheory/chordality/tests/test_intervaldfs.py
graphtheory/chordality/tests/test_intervaltools.py
graphtheory/chordality/tests/test_mcsm.py
graphtheory/chordality/tests/test_mdotools.py
graphtheory/chordality/tests/test_peotools.py
graphtheory/chordality/tests/test_tdtools.py
graphtheory/chordality/tests/tester1.py
graphtheory-1.0.4.dist-info/LICENSE
graphtheory-1.0.4.dist-info/METADATA
graphtheory-1.0.4.dist-info/WHEEL
graphtheory-1.0.4.dist-info/top_level.txt
graphtheory-1.0.4.dist-info/RECORD
