Metadata-Version: 2.1
Name: graphtheory
Version: 1.0.4
Summary: Python implementation of graph data structures and algorithms
Home-page: https://github.com/ufkapano/graphtheory
Author: Andrzej Kapanowski
Author-email: andrzej.kapanowski@uj.edu.pl
Classifier: Programming Language :: Python :: 3
Classifier: License :: OSI Approved :: BSD License
Classifier: Operating System :: OS Independent
Classifier: Topic :: Education
Classifier: Topic :: Scientific/Engineering
Requires-Python: >=3.7
License-File: LICENSE
Requires-Dist: numpy
Requires-Dist: matplotlib
